datasets/__init__.py
datasets/cifar10/__init__.py
datasets/cifar10/data_loader.py
datasets/cifar10/main.py
datasets/cifar10/model_loader.py
datasets/cifar10/models/__init__.py
datasets/cifar10/models/densenet.py
datasets/cifar10/models/resnet.py
datasets/cifar10/models/vgg.py
datasets/cinic10/__init__.py
datasets/cinic10/data_loader.py
datasets/cinic10/main.py
datasets/cinic10/model_loader.py
datasets/cinic10/models/__init__.py
datasets/cinic10/models/baselines.py
loss_landscape-0.0.5.dist-info/LICENSE
loss_landscape-0.0.5.dist-info/METADATA
loss_landscape-0.0.5.dist-info/WHEEL
loss_landscape-0.0.5.dist-info/top_level.txt
loss_landscape-0.0.5.dist-info/RECORD
