Metadata-Version: 2.1
Name: loss-landscape
Version: 0.0.5
Summary: A library for computing loss landscapes for neural networks
Home-page: https://github.com/JoelNiklaus/loss_landscape
Author: Joel Niklaus
Author-email: me@joelniklaus.ch
License: MIT License
Platform: UNKNOWN
Classifier: Programming Language :: Python :: 3
Classifier: License :: OSI Approved :: MIT License
Classifier: Operating System :: OS Independent
Requires-Dist: numpy (==1.18.4)
Requires-Dist: h5py (==2.10.0)
Requires-Dist: matplotlib (==3.2.1)
Requires-Dist: scipy (==1.4.1)
Requires-Dist: scikit-learn (==0.22.2.post1)
Requires-Dist: seaborn (==0.10.1)
